Metadata-Version: 2.1
Name: battlesnake-builder
Version: 0.1.2
Summary: Easily build a BattleSnake
Home-page: https://github.com/Tch1b0/battlesnake-builder
Author: Johannes Pour
Author-email: Johannes@ben11.de
License: MIT
Platform: UNKNOWN
License-File: LICENSE
